langchain_0g/__init__.py
langchain_0g/chat_models/__init__.py
langchain_0g/chat_models/base.py
langchain_0g/llms/__init__.py
langchain_0g/llms/base.py
langchain_0g-0.1.0.dist-info/METADATA
langchain_0g-0.1.0.dist-info/WHEEL
langchain_0g-0.1.0.dist-info/RECORD
