Metadata-Version: 2.4
Name: langchain-0g
Version: 0.1.0
Summary: Official Langchain client for 0g.ai Inference SDK
Author: George Kasparyants
Author-email: gg_plastt@mail.ru
Requires-Python: >=3.10,<4.0
Classifier: Programming Language :: Python :: 3
Classifier: Programming Language :: Python :: 3.10
Classifier: Programming Language :: Python :: 3.11
Classifier: Programming Language :: Python :: 3.12
Classifier: Programming Language :: Python :: 3.13
Classifier: Programming Language :: Python :: 3.14
Provides-Extra: dev
Provides-Extra: test
Requires-Dist: isort (>=5.0.0) ; extra == "dev"
Requires-Dist: mypy (>=1.0.0) ; extra == "dev"
Requires-Dist: pytest (>=6.0) ; extra == "dev"
Requires-Dist: pytest (>=6.0) ; extra == "test"
Requires-Dist: pytest-asyncio (>=0.20.0) ; extra == "dev"
Requires-Dist: pytest-asyncio (>=0.20.0) ; extra == "test"
Requires-Dist: python-0g[langchain] (>=0.6.1.2,<0.7.0.0)
Requires-Dist: python-dotenv (>=0.19.0) ; extra == "dev"
Requires-Dist: python-dotenv (>=0.19.0) ; extra == "test"
Requires-Dist: ruff (>=0.1.0) ; extra == "dev"
